MANIFEST.in
README.md
setup.cfg
setup.py
arabicscript/ArabChar.py
arabicscript/ArabStr.py
arabicscript/ArabicChar.py
arabicscript/ArabicCharacters.py
arabicscript/ArabicShaping.py
arabicscript/BaseForm.py
arabicscript/Char.py
arabicscript/Joining.py
arabicscript/__init__.py
arabicscript/constructors.py
arabicscript.egg-info/PKG-INFO
arabicscript.egg-info/SOURCES.txt
arabicscript.egg-info/dependency_links.txt
arabicscript.egg-info/not-zip-safe
arabicscript.egg-info/top_level.txt