Metadata-Version: 1.1
Name: arabicscript
Version: 0.1.4
Summary: Tools for Arabic script
Home-page: https://github.com/arnizamani/arabicscript
Author: Abdul Rahim Nizamani
Author-email: abdulrahimnizamani@gmail.com
License: GPL
Keywords: Arabic,writing script,Unicode,text processing
Platform: UNKNOWN
Classifier: Development Status :: 2 - Pre-Alpha
Classifier: Intended Audience :: Developers
Classifier: License :: OSI Approved :: GNU General Public License (GPL)
Classifier: Programming Language :: Python :: 3.5
Classifier: Topic :: Text Processing :: Linguistic
